COPYING
MANIFEST.in
README.rst
requirements.txt
setup.py
common/__init__.py
common/admin_custom_actions.py
common/app_label_renamer.py
common/big_integer_field.py
common/common_constants.py
common/common_forms.py
common/common_functions.py
common/custom_xml_emitter.py
common/filter_persist_middleware.py
common/intermediate_model_base_class.py
common/language_field.py
common/only_one_task.py
common/utils.py
common/widgets.py
common/templatetags/__init__.py
common/templatetags/common_tags.py
switch2bill_common.egg-info/PKG-INFO
switch2bill_common.egg-info/SOURCES.txt
switch2bill_common.egg-info/dependency_links.txt
switch2bill_common.egg-info/entry_points.txt
switch2bill_common.egg-info/requires.txt
switch2bill_common.egg-info/top_level.txt