Metadata-Version: 1.1
Name: switch2bill-common
Version: 2.8.0
Summary: Common Django/Python helpers for Star2Billing projects
Home-page: http://github.com/Star2Billing/switch2bill-common
Author: Belaid Arezqui
Author-email: areski@gmail.com
License: MPL 2.0 License
Platform: UNKNOWN
Classifier: Development Status :: 5 - Production/Stable
Classifier: Framework :: Django
Classifier: Intended Audience :: Developers
Classifier: Environment :: Web Environment
Classifier: License :: OSI Approved :: Mozilla Public License 2.0 (MPL 2.0)
Classifier: Operating System :: OS Independent
Classifier: Programming Language :: Python
Classifier: Topic :: Software Development :: Libraries :: Python Modules
